xset/__init__.py
x_set-0.9.dist-info/METADATA
x_set-0.9.dist-info/WHEEL
x_set-0.9.dist-info/top_level.txt
x_set-0.9.dist-info/RECORD
