Metadata-Version: 2.1
Name: x-set
Version: 0.9
Summary: this is a simple pip modul and test
